<!DOCTYPE html PUBLIC "-//W3C//DTD XHTML 1.0 Transitional//EN" "http://www.w3.org/TR/xhtml1/DTD/xhtml1-transitional.dtd">
<html
xmlns="http://www.w3.org/1999/xhtml"
xmlns:bknr="http://bknr.net/"
xmlns:ruinwesen="http://ruinwesen.com/"
lang="en">

<ruinwesen:html-header title="MidiDuino Environment - Program your MiniCommand"/>

<body>
<div class="container">
  <ruinwesen:header/>
  <ruinwesen:navigation/>

<div class="content">
  <ruinwesen:banner/>
			<div class="contenttext">
<div style="clear:both">
  </div>

				<div class="product">
					<div class="producttitle">MIDIDUINO</div><span class="priceright">Program your MiniCommand</span>
					
					<div class="banner2" align="center"><img src="/images/mini-command-banner-slim.png" alt="Banner"/></div>
					
<p>The MiniCommand environment allows you to program your own
					firmwares for the MiniCommand. Use the powerful Ruin &amp;
					Wesen libraries to send and receive MIDI messages, write
					your own sequencers, access the internal SD-Card storage,
					and create easy GUIs for the MiniCommand. Also included is
					an extensive library for controlling the Elektron
					MachineDrum, allowing you to control every possible
					parameter, store and load patterns, songs and kits, and
					fully leverage the possibilities of this machine. Support
					for additional grooveboxes and synthesizers will be added in
					the future.  The whole environment is based on the Arduino
					environment, however all the code running on the MiniCommand
					has been written from scratch for best performance and
					usability. MidiDuino is entirely opensource, and you can
					check out the sourcecode from <a
					 href="http://github.com/wesen/">github</a>.  </p>
					
					<div style="clear: both">
  <h5 class="supportlead">DOWNLOADS</h5>

<div class="supportcol1" style="height: 34px">
  <ul>
    <li><a
  href="http://ruinwesen.com/support-files/minicommand/mididuino-013-windows.zip"
  title="MidiDuino 013 Windows">MidiDuino 013 for Windows</a></li>
    <li><a
  href="http://ruinwesen.com/support-files/minicommand/mididuino-0013-mac.zip"
  title="MidiDuino 013 MacOSX">MidiDuino 013 for MacOSX</a></li>
  </ul>
</div>
<div class="supportcol2" style="height: 34px">
  <ul>
    <li><a
  href="http://ruinwesen.com/support-files/minicommand/minicommand-preliminary.pdf"
  title="MidiDuino Documentaiton">MidiDuino Documentation</a></li>
    <li><a href="http://ruinwesen.com/minicommandfaq" title="MiniCommand FAQ">MiniCommand FAQ</a></li>
  </ul>					
</div>



<div class="supportcol1" style="height: 52px">
  <ul>
    <li><a
  href="http://ruinwesen.com/support-files/patchmanager-win2.zip"
  title="PatchManager for Windows">PatchManager (Windows)</a></li>
    <li><a
  href="http://ruinwesen.com/support-files/patchmanager-macosx3.zip"
  title="PatchManager for MACOSX">PatchManager (MacOSX)</a></li>
    <li><a
  href="http://ruinwesen.com/support-files/patchmanager-linux.zip"
  title="PatchManager for Linux">PatchManager (Linux)</a></li>
  </ul>
</div>
<div class="supportcol2" style="height: 52px">
  <ul>
  </ul>					
</div>
</div>


					<div style="clear: both">
</div>



</div>
		
			</div>
			
<ruinwesen:footer/>
</div>	

</div>
<ruinwesen:google-analytics/>

</body>
</html>
